kst1/__init__.py
kst1/admin.py
kst1/apps.py
kst1/fields.py
kst1/forms.py
kst1/models.py
kst1/states.py
kst1/tests.py
kst1/views.py
kst1/migrations/__init__.py
usha_indian_states_25/__init__.py
usha_indian_states_25/asgi.py
usha_indian_states_25/settings.py
usha_indian_states_25/urls.py
usha_indian_states_25/wsgi.py
usha_indian_states_25-0.2.dist-info/METADATA
usha_indian_states_25-0.2.dist-info/WHEEL
usha_indian_states_25-0.2.dist-info/top_level.txt
usha_indian_states_25-0.2.dist-info/RECORD
