Metadata-Version: 2.2
Name: usha_indian_states_25
Version: 0.2
Summary: A Django app that provides Indian state choices as a model and form field.
Author: Usha
Author-email: ushampro93441@gmail.com
License: MIT
Classifier: Framework :: Django
Classifier: Programming Language :: Python :: 3
Requires-Dist: django
Dynamic: author
Dynamic: author-email
Dynamic: classifier
Dynamic: license
Dynamic: requires-dist
Dynamic: summary
